punctuation/Punctuation.py
punctuation/__init__.py
punctuation_remove-0.0.5.dist-info/LICENSE
punctuation_remove-0.0.5.dist-info/METADATA
punctuation_remove-0.0.5.dist-info/WHEEL
punctuation_remove-0.0.5.dist-info/top_level.txt
punctuation_remove-0.0.5.dist-info/RECORD
