Metadata-Version: 2.1
Name: punctuation-remove
Version: 0.0.5
Summary: Punctuation
Home-page: https://github.com/talhashaikh5/Punctuation.git
Author: Talha Shaikh
Author-email: talha.shaikh5@gmail.com
License: UNKNOWN
Platform: UNKNOWN
Classifier: Programming Language :: Python :: 3
Classifier: License :: OSI Approved :: MIT License
Classifier: Operating System :: OS Independent
